releasenotes/__init__.py
releasenotes/__version__.py
releasenotes/admin.py
releasenotes/apps.py
releasenotes/config.py
releasenotes/models.py
releasenotes/tests.py
releasenotes/urls.py
releasenotes/views.py
releasenotes/migrations/0001_initial.py
releasenotes/migrations/0002_auto_20201126_1536.py
releasenotes/migrations/__init__.py
releasenotes/templates/releasenotes/base.html
releasenotes/templates/releasenotes/index.html
releasenotes/templates/releasenotes/project_detail.html
releasenotes/templates/releasenotes/release_detail.html
django_release_notes-0.1.6.dist-info/LICENSE.mit.txt
django_release_notes-0.1.6.dist-info/METADATA
django_release_notes-0.1.6.dist-info/WHEEL
django_release_notes-0.1.6.dist-info/top_level.txt
django_release_notes-0.1.6.dist-info/RECORD
